{
    "1997-06-01|1998-12-30": [
        {
            "aliases": null,
            "api_detail_url": "https://comicvine.gamespot.com/api/issue/4000-396092/",
            "cover_date": "1997-10-07",
            "date_added": "2013-04-05 14:48:53",
            "date_last_updated": "2013-04-07 06:50:23",
            "deck": "Contains : X-Men Omega (1995)",
            "description": "  ",
            "has_staff_review": false,
            "id": 396092,
            "image": {
                "icon_url": "https://comicvine.gamespot.com/api/image/square_avatar/2964894-fabulosos-x-men-22_10.jpg",
                "medium_url": "https://comicvine.gamespot.com/api/image/scale_medium/2964894-fabulosos-x-men-22_10.jpg",
                "screen_url": "https://comicvine.gamespot.com/api/image/screen_medium/2964894-fabulosos-x-men-22_10.jpg",
                "screen_large_url": "https://comicvine.gamespot.com/api/image/screen_kubrick/2964894-fabulosos-x-men-22_10.jpg",
                "small_url": "https://comicvine.gamespot.com/api/image/scale_small/2964894-fabulosos-x-men-22_10.jpg",
                "super_url": "https://comicvine.gamespot.com/api/image/scale_large/2964894-fabulosos-x-men-22_10.jpg",
                "thumb_url": "https://comicvine.gamespot.com/api/image/scale_avatar/2964894-fabulosos-x-men-22_10.jpg",
                "tiny_url": "https://comicvine.gamespot.com/api/image/square_mini/2964894-fabulosos-x-men-22_10.jpg",
                "original_url": "https://comicvine.gamespot.com/api/image/original/2964894-fabulosos-x-men-22_10.jpg",
                "image_tags": "All Images"
            },
            "issue_number": "22",
            "name": null,
            "site_detail_url": "https://comicvine.gamespot.com/os-fabulosos-x-men-22/4000-396092/",
            "store_date": "1997-10-08",
            "volume": {
                "api_detail_url": "https://comicvine.gamespot.com/api/volume/4050-59622/",
                "id": 59622,
                "name": "Os Fabulosos X-Men",
                "site_detail_url": "https://comicvine.gamespot.com/os-fabulosos-x-men/4050-59622/"
            }
        },
        {
            "aliases": null,
            "api_detail_url": "https://comicvine.gamespot.com/api/issue/4000-534619/",
            "cover_date": "1998-12-16",
            "date_added": "2016-06-08 20:15:30",
            "date_last_updated": "2016-08-21 22:18:46",
            "deck": null,
            "description": null,
            "has_staff_review": false,
            "id": 534619,
            "image": {
                "icon_url": "https://comicvine.gamespot.com/api/image/square_avatar/5255735-22.jpg",
                "medium_url": "https://comicvine.gamespot.com/api/image/scale_medium/5255735-22.jpg",
                "screen_url": "https://comicvine.gamespot.com/api/image/screen_medium/5255735-22.jpg",
                "screen_large_url": "https://comicvine.gamespot.com/api/image/screen_kubrick/5255735-22.jpg",
                "small_url": "https://comicvine.gamespot.com/api/image/scale_small/5255735-22.jpg",
                "super_url": "https://comicvine.gamespot.com/api/image/scale_large/5255735-22.jpg",
                "thumb_url": "https://comicvine.gamespot.com/api/image/scale_avatar/5255735-22.jpg",
                "tiny_url": "https://comicvine.gamespot.com/api/image/square_mini/5255735-22.jpg",
                "original_url": "https://comicvine.gamespot.com/api/image/original/5255735-22.jpg",
                "image_tags": "All Images"
            },
            "issue_number": "22",
            "name": null,
            "site_detail_url": "https://comicvine.gamespot.com/itazura-na-kiss-22/4000-534619/",
            "store_date": "1998-12-16",
            "volume": {
                "api_detail_url": "https://comicvine.gamespot.com/api/volume/4050-91160/",
                "id": 91160,
                "name": "Itazura na Kiss",
                "site_detail_url": "https://comicvine.gamespot.com/itazura-na-kiss/4050-91160/"
            }
        },
        {
            "aliases": null,
            "api_detail_url": "https://comicvine.gamespot.com/api/issue/4000-542141/",
            "cover_date": "1997-11-04",
            "date_added": "2016-07-30 21:49:59",
            "date_last_updated": "2016-07-31 00:23:50",
            "deck": null,
            "description": null,
            "has_staff_review": false,
            "id": 542141,
            "image": {
                "icon_url": "https://comicvine.gamespot.com/api/image/square_avatar/5351656-22.jpg",
                "medium_url": "https://comicvine.gamespot.com/api/image/scale_medium/5351656-22.jpg",
                "screen_url": "https://comicvine.gamespot.com/api/image/screen_medium/5351656-22.jpg",
                "screen_large_url": "https://comicvine.gamespot.com/api/image/screen_kubrick/5351656-22.jpg",
                "small_url": "https://comicvine.gamespot.com/api/image/scale_small/5351656-22.jpg",
                "super_url": "https://comicvine.gamespot.com/api/image/scale_large/5351656-22.jpg",
                "thumb_url": "https://comicvine.gamespot.com/api/image/scale_avatar/5351656-22.jpg",
                "tiny_url": "https://comicvine.gamespot.com/api/image/square_mini/5351656-22.jpg",
                "original_url": "https://comicvine.gamespot.com/api/image/original/5351656-22.jpg",
                "image_tags": "All Images"
            },
            "issue_number": "22",
            "name": "Vol. 22",
            "site_detail_url": "https://comicvine.gamespot.com/zero-the-man-of-the-creation-22-vol-22/4000-542141/",
            "store_date": "1997-11-04",
            "volume": {
                "api_detail_url": "https://comicvine.gamespot.com/api/volume/4050-92672/",
                "id": 92672,
                "name": "Zero: The Man of the Creation",
                "site_detail_url": "https://comicvine.gamespot.com/zero-the-man-of-the-creation/4050-92672/"
            }
        }
    ]
}
