{
    "2015-01-01|2015-12-30": [
        {
            "aliases": null,
            "api_detail_url": "https://comicvine.gamespot.com/api/issue/4000-475822/",
            "cover_date": "2015-01-10",
            "date_added": "2015-01-11 22:29:07",
            "date_last_updated": "2015-01-11 22:32:43",
            "deck": null,
            "description": "<p><em>In part one of \"Fiend of the Masquerade Festival,\" Batman and Robin pursue an escaped convict to a public event, only to find that he's been killed. In a place where everyone is in disguise, how will they find the killer?</em></p>",
            "has_staff_review": false,
            "id": 475822,
            "image": {
                "icon_url": "https://comicvine.gamespot.com/api/image/square_avatar/4324471-28.jpg",
                "medium_url": "https://comicvine.gamespot.com/api/image/scale_medium/4324471-28.jpg",
                "screen_url": "https://comicvine.gamespot.com/api/image/screen_medium/4324471-28.jpg",
                "screen_large_url": "https://comicvine.gamespot.com/api/image/screen_kubrick/4324471-28.jpg",
                "small_url": "https://comicvine.gamespot.com/api/image/scale_small/4324471-28.jpg",
                "super_url": "https://comicvine.gamespot.com/api/image/scale_large/4324471-28.jpg",
                "thumb_url": "https://comicvine.gamespot.com/api/image/scale_avatar/4324471-28.jpg",
                "tiny_url": "https://comicvine.gamespot.com/api/image/square_mini/4324471-28.jpg",
                "original_url": "https://comicvine.gamespot.com/api/image/original/4324471-28.jpg",
                "image_tags": "All Images"
            },
            "issue_number": "28",
            "name": "Fiend of the Masquerade Festival Chapter 1 of 3",
            "site_detail_url": "https://comicvine.gamespot.com/batman-the-jiro-kuwata-batmanga-28-fiend-of-the-ma/4000-475822/",
            "store_date": "2015-01-10",
            "volume": {
                "api_detail_url": "https://comicvine.gamespot.com/api/volume/4050-75410/",
                "id": 75410,
                "name": "Batman: The Jiro Kuwata Batmanga",
                "site_detail_url": "https://comicvine.gamespot.com/batman-the-jiro-kuwata-batmanga/4050-75410/"
            }
        },
        {
            "aliases": null,
            "api_detail_url": "https://comicvine.gamespot.com/api/issue/4000-475978/",
            "cover_date": "2015-01-31",
            "date_added": "2015-01-13 00:05:08",
            "date_last_updated": "2018-05-19 05:28:01",
            "deck": null,
            "description": "<p><em>It’s the epic conclusion to the Bravest Warriors’ battle to save the planet Vira alongside all-new, super-rad ally, Peach. Giant monsters versus giant robots, Bravest Warriors style!</em></p><h4>List of covers and their creators:</h4><table data-max-width=\"true\"><thead><tr><th scope=\"col\">Cover</th><th scope=\"col\">Name</th><th scope=\"col\">Creator(s)</th><th scope=\"col\">Sidebar Location</th></tr></thead><tbody><tr><td>Reg</td><td>Regular Cover</td><td>Ian McGinty (a) &amp; Fred Stresing (c)</td><td>1</td></tr><tr><td>Var</td><td>Variant Cover</td><td>Priscilla Wong</td><td>2</td></tr><tr><td>Var</td><td>Variant Cover</td><td>Rachael Hunt</td><td>3</td></tr></tbody></table>",
            "has_staff_review": false,
            "id": 475978,
            "image": {
                "icon_url": "https://comicvine.gamespot.com/api/image/square_avatar/4326546-28a.jpg",
                "medium_url": "https://comicvine.gamespot.com/api/image/scale_medium/4326546-28a.jpg",
                "screen_url": "https://comicvine.gamespot.com/api/image/screen_medium/4326546-28a.jpg",
                "screen_large_url": "https://comicvine.gamespot.com/api/image/screen_kubrick/4326546-28a.jpg",
                "small_url": "https://comicvine.gamespot.com/api/image/scale_small/4326546-28a.jpg",
                "super_url": "https://comicvine.gamespot.com/api/image/scale_large/4326546-28a.jpg",
                "thumb_url": "https://comicvine.gamespot.com/api/image/scale_avatar/4326546-28a.jpg",
                "tiny_url": "https://comicvine.gamespot.com/api/image/square_mini/4326546-28a.jpg",
                "original_url": "https://comicvine.gamespot.com/api/image/original/4326546-28a.jpg",
                "image_tags": "All Images"
            },
            "issue_number": "28",
            "name": "[Untitled]; Lunch",
            "site_detail_url": "https://comicvine.gamespot.com/bravest-warriors-28-untitled-lunch/4000-475978/",
            "store_date": "2015-01-14",
            "volume": {
                "api_detail_url": "https://comicvine.gamespot.com/api/volume/4050-53346/",
                "id": 53346,
                "name": "Bravest Warriors",
                "site_detail_url": "https://comicvine.gamespot.com/bravest-warriors/4050-53346/"
            }
        },
        {
            "aliases": null,
            "api_detail_url": "https://comicvine.gamespot.com/api/issue/4000-478641/",
            "cover_date": "2015-02-28",
            "date_added": "2015-02-03 00:34:28",
            "date_last_updated": "2015-02-21 11:51:11",
            "deck": null,
            "description": "<p><em>The Titans have returned and are laying waste to the original realms of the Gods. With their immortality gone, and their ranks thinning quickly, desperate measures may be the only option. Can they get past a lifetime of hubris and hatred to unite the pantheons to fight the unbeatable foes?</em></p><p><em>Available with a Regular, End of Days, Iconic, and Gilded Retailer Incentive covers by Jacen Burrows, a Carnage Wraparound cover by German Nobile, a special Enchanting cover by Facundo Percio.</em></p><h4>List of covers and their creators:</h4><table data-max-width=\"true\"><thead><tr><th scope=\"col\">Cover</th><th scope=\"col\">Name</th><th scope=\"col\">Creator(s)</th><th scope=\"col\">Sidebar Location</th></tr></thead><tbody><tr><td>Reg</td><td>Regular Cover</td><td>Jacen Burrows</td><td>1</td></tr><tr><td>EoD</td><td>End of Days Cover</td><td>Jacen Burrows</td><td>2</td></tr><tr><td>Iconic</td><td>Iconic Cover</td><td>Jacen Burrows</td><td>3</td></tr><tr><td>RI</td><td>Gilded Retailer Incentive Cover</td><td>Jacen Burrows</td><td>4</td></tr><tr><td>Wrap</td><td>Carnage Wraparound Cover</td><td>German Nobile</td><td>5</td></tr><tr><td>EC</td><td>Enchanting Cover</td><td>Facundo Percio</td><td>6</td></tr></tbody></table><p>*Medusa appears on cover only.</p>",
            "has_staff_review": false,
            "id": 478641,
            "image": {
                "icon_url": "https://comicvine.gamespot.com/api/image/square_avatar/4370438-28.jpg",
                "medium_url": "https://comicvine.gamespot.com/api/image/scale_medium/4370438-28.jpg",
                "screen_url": "https://comicvine.gamespot.com/api/image/screen_medium/4370438-28.jpg",
                "screen_large_url": "https://comicvine.gamespot.com/api/image/screen_kubrick/4370438-28.jpg",
                "small_url": "https://comicvine.gamespot.com/api/image/scale_small/4370438-28.jpg",
                "super_url": "https://comicvine.gamespot.com/api/image/scale_large/4370438-28.jpg",
                "thumb_url": "https://comicvine.gamespot.com/api/image/scale_avatar/4370438-28.jpg",
                "tiny_url": "https://comicvine.gamespot.com/api/image/square_mini/4370438-28.jpg",
                "original_url": "https://comicvine.gamespot.com/api/image/original/4370438-28.jpg",
                "image_tags": "All Images"
            },
            "issue_number": "28",
            "name": null,
            "site_detail_url": "https://comicvine.gamespot.com/god-is-dead-28/4000-478641/",
            "store_date": "2015-02-04",
            "volume": {
                "api_detail_url": "https://comicvine.gamespot.com/api/volume/4050-67042/",
                "id": 67042,
                "name": "God Is Dead",
                "site_detail_url": "https://comicvine.gamespot.com/god-is-dead/4050-67042/"
            }
        },
        {
            "aliases": null,
            "api_detail_url": "https://comicvine.gamespot.com/api/issue/4000-481580/",
            "cover_date": "2015-03-01",
            "date_added": "2015-03-02 20:58:23",
            "date_last_updated": "2015-03-04 07:20:05",
            "deck": null,
            "description": "<p><em>Dana's quest for revenge leads her to a massive conspiracy. Em deals with getting what she asked for, and finds out that nothing stays buried in a town where the dead live.</em></p>",
            "has_staff_review": false,
            "id": 481580,
            "image": {
                "icon_url": "https://comicvine.gamespot.com/api/image/square_avatar/4425881-revival.jpg",
                "medium_url": "https://comicvine.gamespot.com/api/image/scale_medium/4425881-revival.jpg",
                "screen_url": "https://comicvine.gamespot.com/api/image/screen_medium/4425881-revival.jpg",
                "screen_large_url": "https://comicvine.gamespot.com/api/image/screen_kubrick/4425881-revival.jpg",
                "small_url": "https://comicvine.gamespot.com/api/image/scale_small/4425881-revival.jpg",
                "super_url": "https://comicvine.gamespot.com/api/image/scale_large/4425881-revival.jpg",
                "thumb_url": "https://comicvine.gamespot.com/api/image/scale_avatar/4425881-revival.jpg",
                "tiny_url": "https://comicvine.gamespot.com/api/image/square_mini/4425881-revival.jpg",
                "original_url": "https://comicvine.gamespot.com/api/image/original/4425881-revival.jpg",
                "image_tags": "All Images"
            },
            "issue_number": "28",
            "name": null,
            "site_detail_url": "https://comicvine.gamespot.com/revival-28/4000-481580/",
            "store_date": "2015-03-04",
            "volume": {
                "api_detail_url": "https://comicvine.gamespot.com/api/volume/4050-50379/",
                "id": 50379,
                "name": "Revival",
                "site_detail_url": "https://comicvine.gamespot.com/revival/4050-50379/"
            }
        },
        {
            "aliases": null,
            "api_detail_url": "https://comicvine.gamespot.com/api/issue/4000-482291/",
            "cover_date": "2015-03-12",
            "date_added": "2015-03-11 00:03:28",
            "date_last_updated": "2015-03-15 05:50:05",
            "deck": null,
            "description": "<p><em>The dragons of Sostratos were decimated in a battle between Amazons and humans. Now the sole survivor is taking his revenge on Diana!</em></p>",
            "has_staff_review": false,
            "id": 482291,
            "image": {
                "icon_url": "https://comicvine.gamespot.com/api/image/square_avatar/4442100-28.jpg",
                "medium_url": "https://comicvine.gamespot.com/api/image/scale_medium/4442100-28.jpg",
                "screen_url": "https://comicvine.gamespot.com/api/image/screen_medium/4442100-28.jpg",
                "screen_large_url": "https://comicvine.gamespot.com/api/image/screen_kubrick/4442100-28.jpg",
                "small_url": "https://comicvine.gamespot.com/api/image/scale_small/4442100-28.jpg",
                "super_url": "https://comicvine.gamespot.com/api/image/scale_large/4442100-28.jpg",
                "thumb_url": "https://comicvine.gamespot.com/api/image/scale_avatar/4442100-28.jpg",
                "tiny_url": "https://comicvine.gamespot.com/api/image/square_mini/4442100-28.jpg",
                "original_url": "https://comicvine.gamespot.com/api/image/original/4442100-28.jpg",
                "image_tags": "All Images"
            },
            "issue_number": "28",
            "name": "Casualties of War",
            "site_detail_url": "https://comicvine.gamespot.com/sensation-comics-featuring-wonder-woman-28-casualt/4000-482291/",
            "store_date": "2015-03-12",
            "volume": {
                "api_detail_url": "https://comicvine.gamespot.com/api/volume/4050-76430/",
                "id": 76430,
                "name": "Sensation Comics Featuring Wonder Woman",
                "site_detail_url": "https://comicvine.gamespot.com/sensation-comics-featuring-wonder-woman/4050-76430/"
            }
        },
        {
            "aliases": null,
            "api_detail_url": "https://comicvine.gamespot.com/api/issue/4000-482712/",
            "cover_date": "2015-02-28",
            "date_added": "2015-03-17 00:06:50",
            "date_last_updated": "2015-05-10 08:05:07",
            "deck": null,
            "description": "<p><em>The long run is over, and Dredd wants Chief Justice Cal to answer for his crimes! But Mega-City One is already in twitchy, paranoid chaos (namely thanks to the events of the previous 27 issues). What will the news of Cal’s deceptions do to the soul of the city? That’s when Judge Anderson comes up with a shocking solution that could change the Meg forever…</em></p><h4>List of covers and their creators:</h4><table data-max-width=\"true\"><thead><tr><th scope=\"col\">Cover</th><th scope=\"col\">Name</th><th scope=\"col\">Creator(s)</th><th scope=\"col\">Sidebar Location</th></tr></thead><tbody><tr><td>Reg</td><td>Regular Cover</td><td>Mark Torres</td><td>1</td></tr><tr><td>Sub</td><td>Subscription Cover</td><td>James O'Barr</td><td>2</td></tr></tbody></table>",
            "has_staff_review": false,
            "id": 482712,
            "image": {
                "icon_url": "https://comicvine.gamespot.com/api/image/square_avatar/4452923-28.jpg",
                "medium_url": "https://comicvine.gamespot.com/api/image/scale_medium/4452923-28.jpg",
                "screen_url": "https://comicvine.gamespot.com/api/image/screen_medium/4452923-28.jpg",
                "screen_large_url": "https://comicvine.gamespot.com/api/image/screen_kubrick/4452923-28.jpg",
                "small_url": "https://comicvine.gamespot.com/api/image/scale_small/4452923-28.jpg",
                "super_url": "https://comicvine.gamespot.com/api/image/scale_large/4452923-28.jpg",
                "thumb_url": "https://comicvine.gamespot.com/api/image/scale_avatar/4452923-28.jpg",
                "tiny_url": "https://comicvine.gamespot.com/api/image/square_mini/4452923-28.jpg",
                "original_url": "https://comicvine.gamespot.com/api/image/original/4452923-28.jpg",
                "image_tags": "All Images"
            },
            "issue_number": "28",
            "name": "Mega-City Manhunt, Part 4: Mental Block",
            "site_detail_url": "https://comicvine.gamespot.com/judge-dredd-28-mega-city-manhunt-part-4-mental-blo/4000-482712/",
            "store_date": "2015-03-18",
            "volume": {
                "api_detail_url": "https://comicvine.gamespot.com/api/volume/4050-54111/",
                "id": 54111,
                "name": "Judge Dredd",
                "site_detail_url": "https://comicvine.gamespot.com/judge-dredd/4050-54111/"
            }
        },
        {
            "aliases": null,
            "api_detail_url": "https://comicvine.gamespot.com/api/issue/4000-482715/",
            "cover_date": "2015-02-28",
            "date_added": "2015-03-17 00:06:57",
            "date_last_updated": "2017-04-25 04:01:17",
            "deck": null,
            "description": "<p><em>Twilight and friends journey to the heart of Everfree Forest to find out what has been causing its inhabitants to flee. What they find can only mean trouble for Ponyville!</em></p><h4>List of covers and their creators:</h4><table data-max-width=\"true\"><thead><tr><th scope=\"col\">Cover</th><th scope=\"col\">Name</th><th scope=\"col\">Creator(s)</th><th scope=\"col\">Sidebar Location</th></tr></thead><tbody><tr><td>A</td><td>Cover A</td><td>Andy Price</td><td>1</td></tr><tr><td>B</td><td>Cover B</td><td>Sara Richard</td><td>2</td></tr><tr><td>RI</td><td>1:10 Retailer Incentive Cover</td><td>Mary Bellamy</td><td>3</td></tr><tr><td>RE</td><td>Hot Topic Exclusive Cover</td><td>Tony Fleecs</td><td>4</td></tr></tbody></table>",
            "has_staff_review": false,
            "id": 482715,
            "image": {
                "icon_url": "https://comicvine.gamespot.com/api/image/square_avatar/4452926-28a.jpg",
                "medium_url": "https://comicvine.gamespot.com/api/image/scale_medium/4452926-28a.jpg",
                "screen_url": "https://comicvine.gamespot.com/api/image/screen_medium/4452926-28a.jpg",
                "screen_large_url": "https://comicvine.gamespot.com/api/image/screen_kubrick/4452926-28a.jpg",
                "small_url": "https://comicvine.gamespot.com/api/image/scale_small/4452926-28a.jpg",
                "super_url": "https://comicvine.gamespot.com/api/image/scale_large/4452926-28a.jpg",
                "thumb_url": "https://comicvine.gamespot.com/api/image/scale_avatar/4452926-28a.jpg",
                "tiny_url": "https://comicvine.gamespot.com/api/image/square_mini/4452926-28a.jpg",
                "original_url": "https://comicvine.gamespot.com/api/image/original/4452926-28a.jpg",
                "image_tags": "All Images"
            },
            "issue_number": "28",
            "name": "The Root of the Problem Part 2: Flower Power",
            "site_detail_url": "https://comicvine.gamespot.com/my-little-pony-friendship-is-magic-28-the-root-of-/4000-482715/",
            "store_date": "2015-03-18",
            "volume": {
                "api_detail_url": "https://comicvine.gamespot.com/api/volume/4050-54320/",
                "id": 54320,
                "name": "My Little Pony: Friendship Is Magic",
                "site_detail_url": "https://comicvine.gamespot.com/my-little-pony-friendship-is-magic/4050-54320/"
            }
        },
        {
            "aliases": null,
            "api_detail_url": "https://comicvine.gamespot.com/api/issue/4000-482924/",
            "cover_date": "2015-02-17",
            "date_added": "2015-03-19 07:28:31",
            "date_last_updated": "2015-03-19 23:37:26",
            "deck": null,
            "description": null,
            "has_staff_review": false,
            "id": 482924,
            "image": {
                "icon_url": "https://comicvine.gamespot.com/api/image/square_avatar/4456973-28.jpg",
                "medium_url": "https://comicvine.gamespot.com/api/image/scale_medium/4456973-28.jpg",
                "screen_url": "https://comicvine.gamespot.com/api/image/screen_medium/4456973-28.jpg",
                "screen_large_url": "https://comicvine.gamespot.com/api/image/screen_kubrick/4456973-28.jpg",
                "small_url": "https://comicvine.gamespot.com/api/image/scale_small/4456973-28.jpg",
                "super_url": "https://comicvine.gamespot.com/api/image/scale_large/4456973-28.jpg",
                "thumb_url": "https://comicvine.gamespot.com/api/image/scale_avatar/4456973-28.jpg",
                "tiny_url": "https://comicvine.gamespot.com/api/image/square_mini/4456973-28.jpg",
                "original_url": "https://comicvine.gamespot.com/api/image/original/4456973-28.jpg",
                "image_tags": "All Images"
            },
            "issue_number": "28",
            "name": "Vol. 28",
            "site_detail_url": "https://comicvine.gamespot.com/c-m-b-28-vol-28/4000-482924/",
            "store_date": "2015-02-17",
            "volume": {
                "api_detail_url": "https://comicvine.gamespot.com/api/volume/4050-80217/",
                "id": 80217,
                "name": "C.M.B.",
                "site_detail_url": "https://comicvine.gamespot.com/c-m-b/4050-80217/"
            }
        },
        {
            "aliases": null,
            "api_detail_url": "https://comicvine.gamespot.com/api/issue/4000-483357/",
            "cover_date": "2015-05-31",
            "date_added": "2015-03-24 00:07:00",
            "date_last_updated": "2017-12-25 16:23:00",
            "deck": null,
            "description": "<p><em>BLACK VORTEX TIE-IN!</em></p><p><em>Nova joins the Guardians of the Galaxy and the X-Men for a huge adventure.</em></p><p><em>With the Black Vortex itself in his possession, Sam goes on the run for his life. Good thing they call him the human rocket!</em></p><h4>List of covers and their creators:</h4><table data-max-width=\"true\"><thead><tr><th scope=\"col\">Cover</th><th scope=\"col\">Name</th><th scope=\"col\">Creator(s)</th><th scope=\"col\">Sidebar Location</th></tr></thead><tbody><tr><td>Reg</td><td>Regular Cover</td><td>Orphans Cheeps</td><td>1</td></tr><tr><td>Var</td><td>Cosmically Enhanced Variant Cover</td><td>Andrea Sorrentino</td><td>2</td></tr></tbody></table>",
            "has_staff_review": false,
            "id": 483357,
            "image": {
                "icon_url": "https://comicvine.gamespot.com/api/image/square_avatar/4466409-28.jpg",
                "medium_url": "https://comicvine.gamespot.com/api/image/scale_medium/4466409-28.jpg",
                "screen_url": "https://comicvine.gamespot.com/api/image/screen_medium/4466409-28.jpg",
                "screen_large_url": "https://comicvine.gamespot.com/api/image/screen_kubrick/4466409-28.jpg",
                "small_url": "https://comicvine.gamespot.com/api/image/scale_small/4466409-28.jpg",
                "super_url": "https://comicvine.gamespot.com/api/image/scale_large/4466409-28.jpg",
                "thumb_url": "https://comicvine.gamespot.com/api/image/scale_avatar/4466409-28.jpg",
                "tiny_url": "https://comicvine.gamespot.com/api/image/square_mini/4466409-28.jpg",
                "original_url": "https://comicvine.gamespot.com/api/image/original/4466409-28.jpg",
                "image_tags": "All Images"
            },
            "issue_number": "28",
            "name": "The Black Vortex Chapter 8",
            "site_detail_url": "https://comicvine.gamespot.com/nova-28-the-black-vortex-chapter-8/4000-483357/",
            "store_date": "2015-03-25",
            "volume": {
                "api_detail_url": "https://comicvine.gamespot.com/api/volume/4050-57535/",
                "id": 57535,
                "name": "Nova",
                "site_detail_url": "https://comicvine.gamespot.com/nova/4050-57535/"
            }
        },
        {
            "aliases": null,
            "api_detail_url": "https://comicvine.gamespot.com/api/issue/4000-487380/",
            "cover_date": "2015-05-01",
            "date_added": "2015-04-30 08:00:59",
            "date_last_updated": "2016-07-01 03:08:09",
            "deck": null,
            "description": "<h2>Chapter Titles</h2><ul><li>Extra Bub 1 \"You Can Make 100 Friends, Right?\" (友達100人出来るかな? <i>Tomodachi Hyaku Nin Dekiru ka na?</i>)</li><li>Extra Bub 2 \"Badump! It's All Ishiyama Up in This Beach!\" (ドキッ♥石矢魔だらけの海水浴場! <i>Doki' Ishiyama Darake no Kaisui Yokujō!</i>)</li><li>Extra Bub 3 \"The Diary of the Ishiyama Boys Adrift at Sea\" (石矢魔少年漂流記 <i>Ishiyama Shōnen Hyōryūki</i>)</li><li>Extra Bub 4 \"Furuichi the Hero\" (古市・ザ・ヒーロー <i>Furuichi za Hīrō</i>)</li><li>Extra Bub 5 \"Love Blooms in the Season of Partings\" (別れの季節に恋は咲く!! <i>Wakare no Kisetsu ni Koi wa Saku!!</i>)</li><li>Extra Bub 6 \"Parent and Child\" (親と子 <i>Oya to Ko</i>)</li></ul>",
            "has_staff_review": false,
            "id": 487380,
            "image": {
                "icon_url": "https://comicvine.gamespot.com/api/image/square_avatar/4536262-28.jpg",
                "medium_url": "https://comicvine.gamespot.com/api/image/scale_medium/4536262-28.jpg",
                "screen_url": "https://comicvine.gamespot.com/api/image/screen_medium/4536262-28.jpg",
                "screen_large_url": "https://comicvine.gamespot.com/api/image/screen_kubrick/4536262-28.jpg",
                "small_url": "https://comicvine.gamespot.com/api/image/scale_small/4536262-28.jpg",
                "super_url": "https://comicvine.gamespot.com/api/image/scale_large/4536262-28.jpg",
                "thumb_url": "https://comicvine.gamespot.com/api/image/scale_avatar/4536262-28.jpg",
                "tiny_url": "https://comicvine.gamespot.com/api/image/square_mini/4536262-28.jpg",
                "original_url": "https://comicvine.gamespot.com/api/image/original/4536262-28.jpg",
                "image_tags": "All Images"
            },
            "issue_number": "28",
            "name": "Parent and Child",
            "site_detail_url": "https://comicvine.gamespot.com/beelzebub-28-parent-and-child/4000-487380/",
            "store_date": "2015-05-01",
            "volume": {
                "api_detail_url": "https://comicvine.gamespot.com/api/volume/4050-42083/",
                "id": 42083,
                "name": "Beelzebub",
                "site_detail_url": "https://comicvine.gamespot.com/beelzebub/4050-42083/"
            }
        },
        {
            "aliases": null,
            "api_detail_url": "https://comicvine.gamespot.com/api/issue/4000-487751/",
            "cover_date": "2015-05-31",
            "date_added": "2015-05-04 07:45:00",
            "date_last_updated": "2015-07-14 16:07:29",
            "deck": null,
            "description": "<p><em>Ruby and Sapphire are back! Professor Birch sends the fabulous duo to help Emerald find the Wish Pokémon Jirachi. But first there are high-pitched Pokémon battles to fight in the Battle Dome Tournament... Then Ruby discovers something surprising about Emerald's Sceptile, and everyone learns the true identity of their arch nemesis, Guile Hideout.</em></p><p><em>Now, who will catch Jirachi...?</em></p><h2>Chapter Titles</h2><ul><li>Adventure 318: Sneaky Like Shedinja II</li><li>Adventure 319: Verily Vanquishing Vileplume I</li><li>Adventure 320: Verily Vanquishing Vileplume II</li><li>Adventure 321: Cunning Kirlia</li><li>Adventure 322: Susceptible to Sceptile</li><li>Adventure 323: A Cheeky Charizard Change-Up I</li><li>Adventure 324: A Cheeky Charizard Change-Up II</li><li>Adventure 325: Standing in the Way with Starmie</li><li>Adventure 326: Lemme at 'Em, Lapras!</li><li>Adventure 327: Facing Gulpin Is Hard To Swallow</li></ul>",
            "has_staff_review": false,
            "id": 487751,
            "image": {
                "icon_url": "https://comicvine.gamespot.com/api/image/square_avatar/4543461-28.jpg",
                "medium_url": "https://comicvine.gamespot.com/api/image/scale_medium/4543461-28.jpg",
                "screen_url": "https://comicvine.gamespot.com/api/image/screen_medium/4543461-28.jpg",
                "screen_large_url": "https://comicvine.gamespot.com/api/image/screen_kubrick/4543461-28.jpg",
                "small_url": "https://comicvine.gamespot.com/api/image/scale_small/4543461-28.jpg",
                "super_url": "https://comicvine.gamespot.com/api/image/scale_large/4543461-28.jpg",
                "thumb_url": "https://comicvine.gamespot.com/api/image/scale_avatar/4543461-28.jpg",
                "tiny_url": "https://comicvine.gamespot.com/api/image/square_mini/4543461-28.jpg",
                "original_url": "https://comicvine.gamespot.com/api/image/original/4543461-28.jpg",
                "image_tags": "All Images"
            },
            "issue_number": "28",
            "name": "Vol. 28",
            "site_detail_url": "https://comicvine.gamespot.com/pokemon-adventures-28-vol-28/4000-487751/",
            "store_date": "2015-05-06",
            "volume": {
                "api_detail_url": "https://comicvine.gamespot.com/api/volume/4050-30148/",
                "id": 30148,
                "name": "Pokémon Adventures",
                "site_detail_url": "https://comicvine.gamespot.com/pokemon-adventures/4050-30148/"
            }
        },
        {
            "aliases": null,
            "api_detail_url": "https://comicvine.gamespot.com/api/issue/4000-487871/",
            "cover_date": "2015-05-31",
            "date_added": "2015-05-05 00:19:01",
            "date_last_updated": "2015-05-05 10:52:54",
            "deck": null,
            "description": "<p><em>What has Cohen been up to since being dismissed from the FBI? Harboring a few grudges with a certain thief…</em></p>",
            "has_staff_review": false,
            "id": 487871,
            "image": {
                "icon_url": "https://comicvine.gamespot.com/api/image/square_avatar/4545330-28.jpg",
                "medium_url": "https://comicvine.gamespot.com/api/image/scale_medium/4545330-28.jpg",
                "screen_url": "https://comicvine.gamespot.com/api/image/screen_medium/4545330-28.jpg",
                "screen_large_url": "https://comicvine.gamespot.com/api/image/screen_kubrick/4545330-28.jpg",
                "small_url": "https://comicvine.gamespot.com/api/image/scale_small/4545330-28.jpg",
                "super_url": "https://comicvine.gamespot.com/api/image/scale_large/4545330-28.jpg",
                "thumb_url": "https://comicvine.gamespot.com/api/image/scale_avatar/4545330-28.jpg",
                "tiny_url": "https://comicvine.gamespot.com/api/image/square_mini/4545330-28.jpg",
                "original_url": "https://comicvine.gamespot.com/api/image/original/4545330-28.jpg",
                "image_tags": "All Images"
            },
            "issue_number": "28",
            "name": null,
            "site_detail_url": "https://comicvine.gamespot.com/thief-of-thieves-28/4000-487871/",
            "store_date": "2015-05-06",
            "volume": {
                "api_detail_url": "https://comicvine.gamespot.com/api/volume/4050-45727/",
                "id": 45727,
                "name": "Thief of Thieves",
                "site_detail_url": "https://comicvine.gamespot.com/thief-of-thieves/4050-45727/"
            }
        },
        {
            "aliases": null,
            "api_detail_url": "https://comicvine.gamespot.com/api/issue/4000-488608/",
            "cover_date": "2015-05-01",
            "date_added": "2015-05-11 21:25:15",
            "date_last_updated": "2016-03-01 12:41:45",
            "deck": null,
            "description": "<p><em>Alana acts.</em></p>",
            "has_staff_review": false,
            "id": 488608,
            "image": {
                "icon_url": "https://comicvine.gamespot.com/api/image/square_avatar/4563135-28.jpg",
                "medium_url": "https://comicvine.gamespot.com/api/image/scale_medium/4563135-28.jpg",
                "screen_url": "https://comicvine.gamespot.com/api/image/screen_medium/4563135-28.jpg",
                "screen_large_url": "https://comicvine.gamespot.com/api/image/screen_kubrick/4563135-28.jpg",
                "small_url": "https://comicvine.gamespot.com/api/image/scale_small/4563135-28.jpg",
                "super_url": "https://comicvine.gamespot.com/api/image/scale_large/4563135-28.jpg",
                "thumb_url": "https://comicvine.gamespot.com/api/image/scale_avatar/4563135-28.jpg",
                "tiny_url": "https://comicvine.gamespot.com/api/image/square_mini/4563135-28.jpg",
                "original_url": "https://comicvine.gamespot.com/api/image/original/4563135-28.jpg",
                "image_tags": "All Images"
            },
            "issue_number": "28",
            "name": "Chapter Twenty-Eight",
            "site_detail_url": "https://comicvine.gamespot.com/saga-28-chapter-twenty-eight/4000-488608/",
            "store_date": "2015-05-13",
            "volume": {
                "api_detail_url": "https://comicvine.gamespot.com/api/volume/4050-46568/",
                "id": 46568,
                "name": "Saga",
                "site_detail_url": "https://comicvine.gamespot.com/saga/4050-46568/"
            }
        },
        {
            "aliases": null,
            "api_detail_url": "https://comicvine.gamespot.com/api/issue/4000-489382/",
            "cover_date": "2015-05-31",
            "date_added": "2015-05-19 02:15:46",
            "date_last_updated": "2015-05-23 03:05:35",
            "deck": null,
            "description": "<p><em>With the arrival of an eclipse, Linus prepares the gang for the worst. Using Charlie Brown’s perfectly round head as a placeholder for the sun, he must do all he can to keep them from staring into the upcoming rays. “Sunny Disposition” and more adventures are in store in this brand-new issue!</em></p><h4>List of covers and their creators:</h4><table data-max-width=\"true\"><thead><tr><th scope=\"col\">Cover</th><th scope=\"col\">Name</th><th scope=\"col\">Creator(s)</th><th scope=\"col\">Sidebar Location</th></tr></thead><tbody><tr><td>Reg</td><td>Regular Cover</td><td>Charles M. Schulz (a) &amp; Kara Leopard (d)</td><td>1</td></tr><tr><td>RE</td><td>\"Stop Calling Me Sir\" First Appearance BOOM! Studios Exclusive Cover</td><td>Charles M. Schulz (a) &amp; Nomi Kane (d)</td><td>2</td></tr></tbody></table>",
            "has_staff_review": false,
            "id": 489382,
            "image": {
                "icon_url": "https://comicvine.gamespot.com/api/image/square_avatar/4580758-28.jpg",
                "medium_url": "https://comicvine.gamespot.com/api/image/scale_medium/4580758-28.jpg",
                "screen_url": "https://comicvine.gamespot.com/api/image/screen_medium/4580758-28.jpg",
                "screen_large_url": "https://comicvine.gamespot.com/api/image/screen_kubrick/4580758-28.jpg",
                "small_url": "https://comicvine.gamespot.com/api/image/scale_small/4580758-28.jpg",
                "super_url": "https://comicvine.gamespot.com/api/image/scale_large/4580758-28.jpg",
                "thumb_url": "https://comicvine.gamespot.com/api/image/scale_avatar/4580758-28.jpg",
                "tiny_url": "https://comicvine.gamespot.com/api/image/square_mini/4580758-28.jpg",
                "original_url": "https://comicvine.gamespot.com/api/image/original/4580758-28.jpg",
                "image_tags": "All Images"
            },
            "issue_number": "28",
            "name": "Studs; Sunny Disposition; Happy Any Day",
            "site_detail_url": "https://comicvine.gamespot.com/peanuts-28-studs-sunny-disposition-happy-any-day/4000-489382/",
            "store_date": "2015-05-20",
            "volume": {
                "api_detail_url": "https://comicvine.gamespot.com/api/volume/4050-51282/",
                "id": 51282,
                "name": "Peanuts",
                "site_detail_url": "https://comicvine.gamespot.com/peanuts/4050-51282/"
            }
        },
        {
            "aliases": null,
            "api_detail_url": "https://comicvine.gamespot.com/api/issue/4000-490692/",
            "cover_date": "2015-06-30",
            "date_added": "2015-06-01 01:55:43",
            "date_last_updated": "2015-06-03 05:48:38",
            "deck": null,
            "description": "<h4><em>The Tiger's Tears</em></h4><p><em>Ichiryu, head of the IGO, and Midora, head of the nefarious Gourmet Corp., were once like brothers under the tutelage of Gourmet God Acacia, but now they are bitter rivals locked in a mortal combat of chopsticks vs. tongue. We take a trip hundreds of years into the past to see just what went wrong when Gourmet God Acacia’s three disciples Ichiryu, Jiro and Midora trained alongside their mentor, Acacia, and God Chef Froese to turn Midora into the monster he is today.</em></p><h2>Chapter Titles</h2><ul><li>Gourmet 244: Puzzling Identity!!</li><li>Gourmet 245: At the End!!</li><li>Gourmet 246: One More Final Battle!!</li><li>Gourmet 247: Ichiryu and Midora Collide!!</li><li>Gourmet 248: Ichiryu's Power!!</li><li>Gourmet 249: Turning of the Tide!!</li><li>Gourmet 250: Bottomless Hunger!!</li><li>Gourmet 251: Acacia and His Three Disciples!!</li><li>Gourmet 252: Acacia's Fairy Tales!!</li><li>Gourmet 253: The Tiger's Tears!!</li></ul>",
            "has_staff_review": false,
            "id": 490692,
            "image": {
                "icon_url": "https://comicvine.gamespot.com/api/image/square_avatar/4598262-28.jpg",
                "medium_url": "https://comicvine.gamespot.com/api/image/scale_medium/4598262-28.jpg",
                "screen_url": "https://comicvine.gamespot.com/api/image/screen_medium/4598262-28.jpg",
                "screen_large_url": "https://comicvine.gamespot.com/api/image/screen_kubrick/4598262-28.jpg",
                "small_url": "https://comicvine.gamespot.com/api/image/scale_small/4598262-28.jpg",
                "super_url": "https://comicvine.gamespot.com/api/image/scale_large/4598262-28.jpg",
                "thumb_url": "https://comicvine.gamespot.com/api/image/scale_avatar/4598262-28.jpg",
                "tiny_url": "https://comicvine.gamespot.com/api/image/square_mini/4598262-28.jpg",
                "original_url": "https://comicvine.gamespot.com/api/image/original/4598262-28.jpg",
                "image_tags": "All Images"
            },
            "issue_number": "28",
            "name": "The Tiger's Tears",
            "site_detail_url": "https://comicvine.gamespot.com/toriko-28-the-tiger-s-tears/4000-490692/",
            "store_date": "2015-06-03",
            "volume": {
                "api_detail_url": "https://comicvine.gamespot.com/api/volume/4050-39219/",
                "id": 39219,
                "name": "Toriko",
                "site_detail_url": "https://comicvine.gamespot.com/toriko/4050-39219/"
            }
        },
        {
            "aliases": null,
            "api_detail_url": "https://comicvine.gamespot.com/api/issue/4000-491691/",
            "cover_date": "2015-06-10",
            "date_added": "2015-06-11 15:50:01",
            "date_last_updated": "2015-10-03 14:07:00",
            "deck": null,
            "description": "<p><em>The Doctor, Martha Jones, Matthew and Emily help U.N.I.T. fight off an Angel race called the Enochians. The Doctor and Emily find the Enochian's buried ship while U.N.I.T. fights off the tree posessed Enochians.</em></p>",
            "has_staff_review": false,
            "id": 491691,
            "image": {
                "icon_url": "https://comicvine.gamespot.com/api/image/square_avatar/4619990-28.jpg",
                "medium_url": "https://comicvine.gamespot.com/api/image/scale_medium/4619990-28.jpg",
                "screen_url": "https://comicvine.gamespot.com/api/image/screen_medium/4619990-28.jpg",
                "screen_large_url": "https://comicvine.gamespot.com/api/image/screen_kubrick/4619990-28.jpg",
                "small_url": "https://comicvine.gamespot.com/api/image/scale_small/4619990-28.jpg",
                "super_url": "https://comicvine.gamespot.com/api/image/scale_large/4619990-28.jpg",
                "thumb_url": "https://comicvine.gamespot.com/api/image/scale_avatar/4619990-28.jpg",
                "tiny_url": "https://comicvine.gamespot.com/api/image/square_mini/4619990-28.jpg",
                "original_url": "https://comicvine.gamespot.com/api/image/original/4619990-28.jpg",
                "image_tags": "All Images"
            },
            "issue_number": "28",
            "name": "Don't Step On the Grass Part 2: Old Friends",
            "site_detail_url": "https://comicvine.gamespot.com/doctor-who-the-tenth-doctor-archives-28-dont-step-/4000-491691/",
            "store_date": "2015-06-10",
            "volume": {
                "api_detail_url": "https://comicvine.gamespot.com/api/volume/4050-82004/",
                "id": 82004,
                "name": "Doctor Who: The Tenth Doctor Archives",
                "site_detail_url": "https://comicvine.gamespot.com/doctor-who-the-tenth-doctor-archives/4050-82004/"
            }
        },
        {
            "aliases": null,
            "api_detail_url": "https://comicvine.gamespot.com/api/issue/4000-492190/",
            "cover_date": "2015-06-17",
            "date_added": "2015-06-16 00:01:56",
            "date_last_updated": "2016-08-16 14:25:02",
            "deck": null,
            "description": "<p><em>Bigby and Snow venture to new territory, where a mysterious and strangely familiar young girl and a magic glowing tree await.</em></p>",
            "has_staff_review": false,
            "id": 492190,
            "image": {
                "icon_url": "https://comicvine.gamespot.com/api/image/square_avatar/4628655-28.jpg",
                "medium_url": "https://comicvine.gamespot.com/api/image/scale_medium/4628655-28.jpg",
                "screen_url": "https://comicvine.gamespot.com/api/image/screen_medium/4628655-28.jpg",
                "screen_large_url": "https://comicvine.gamespot.com/api/image/screen_kubrick/4628655-28.jpg",
                "small_url": "https://comicvine.gamespot.com/api/image/scale_small/4628655-28.jpg",
                "super_url": "https://comicvine.gamespot.com/api/image/scale_large/4628655-28.jpg",
                "thumb_url": "https://comicvine.gamespot.com/api/image/scale_avatar/4628655-28.jpg",
                "tiny_url": "https://comicvine.gamespot.com/api/image/square_mini/4628655-28.jpg",
                "original_url": "https://comicvine.gamespot.com/api/image/original/4628655-28.jpg",
                "image_tags": "All Images"
            },
            "issue_number": "28",
            "name": "Chapter Twenty-Eight; Heart of Glass Part 7: This Woman's Work",
            "site_detail_url": "https://comicvine.gamespot.com/fables-the-wolf-among-us-28-chapter-twenty-eight-h/4000-492190/",
            "store_date": "2015-06-17",
            "volume": {
                "api_detail_url": "https://comicvine.gamespot.com/api/volume/4050-78767/",
                "id": 78767,
                "name": "Fables: The Wolf Among Us",
                "site_detail_url": "https://comicvine.gamespot.com/fables-the-wolf-among-us/4050-78767/"
            }
        },
        {
            "aliases": null,
            "api_detail_url": "https://comicvine.gamespot.com/api/issue/4000-494846/",
            "cover_date": "2015-07-12",
            "date_added": "2015-07-11 03:23:13",
            "date_last_updated": "2015-08-02 18:11:11",
            "deck": null,
            "description": "<p><em>Amidst the chaos arrives Havik's champion...Raiden?! But how can this be?</em></p>",
            "has_staff_review": false,
            "id": 494846,
            "image": {
                "icon_url": "https://comicvine.gamespot.com/api/image/square_avatar/4680804-28.jpg",
                "medium_url": "https://comicvine.gamespot.com/api/image/scale_medium/4680804-28.jpg",
                "screen_url": "https://comicvine.gamespot.com/api/image/screen_medium/4680804-28.jpg",
                "screen_large_url": "https://comicvine.gamespot.com/api/image/screen_kubrick/4680804-28.jpg",
                "small_url": "https://comicvine.gamespot.com/api/image/scale_small/4680804-28.jpg",
                "super_url": "https://comicvine.gamespot.com/api/image/scale_large/4680804-28.jpg",
                "thumb_url": "https://comicvine.gamespot.com/api/image/scale_avatar/4680804-28.jpg",
                "tiny_url": "https://comicvine.gamespot.com/api/image/square_mini/4680804-28.jpg",
                "original_url": "https://comicvine.gamespot.com/api/image/original/4680804-28.jpg",
                "image_tags": "All Images"
            },
            "issue_number": "28",
            "name": "Blood Island Chapter 28: Reiko's Blood Reigns",
            "site_detail_url": "https://comicvine.gamespot.com/mortal-kombat-x-28-blood-island-chapter-28-reikos-/4000-494846/",
            "store_date": "2015-07-12",
            "volume": {
                "api_detail_url": "https://comicvine.gamespot.com/api/volume/4050-79262/",
                "id": 79262,
                "name": "Mortal Kombat X",
                "site_detail_url": "https://comicvine.gamespot.com/mortal-kombat-x/4050-79262/"
            }
        },
        {
            "aliases": null,
            "api_detail_url": "https://comicvine.gamespot.com/api/issue/4000-497091/",
            "cover_date": "2015-08-05",
            "date_added": "2015-08-08 01:06:23",
            "date_last_updated": "2015-10-03 14:03:20",
            "deck": null,
            "description": "<p><em>Amy and Rory's holiday aboard a luxury star-liner has turned into a game of to catch a thief, as class warfare threatens to break out on the ship. And what's the Doctor been distracted with in the bowels of the TARDIS?</em></p>",
            "has_staff_review": false,
            "id": 497091,
            "image": {
                "icon_url": "https://comicvine.gamespot.com/api/image/square_avatar/4733652-28.jpg",
                "medium_url": "https://comicvine.gamespot.com/api/image/scale_medium/4733652-28.jpg",
                "screen_url": "https://comicvine.gamespot.com/api/image/screen_medium/4733652-28.jpg",
                "screen_large_url": "https://comicvine.gamespot.com/api/image/screen_kubrick/4733652-28.jpg",
                "small_url": "https://comicvine.gamespot.com/api/image/scale_small/4733652-28.jpg",
                "super_url": "https://comicvine.gamespot.com/api/image/scale_large/4733652-28.jpg",
                "thumb_url": "https://comicvine.gamespot.com/api/image/scale_avatar/4733652-28.jpg",
                "tiny_url": "https://comicvine.gamespot.com/api/image/square_mini/4733652-28.jpg",
                "original_url": "https://comicvine.gamespot.com/api/image/original/4733652-28.jpg",
                "image_tags": "All Images"
            },
            "issue_number": "28",
            "name": "The Eye of Ashaya: Part 2",
            "site_detail_url": "https://comicvine.gamespot.com/doctor-who-the-eleventh-doctor-archives-28-the-eye/4000-497091/",
            "store_date": "2015-08-05",
            "volume": {
                "api_detail_url": "https://comicvine.gamespot.com/api/volume/4050-82879/",
                "id": 82879,
                "name": "Doctor Who: The Eleventh Doctor Archives",
                "site_detail_url": "https://comicvine.gamespot.com/doctor-who-the-eleventh-doctor-archives/4050-82879/"
            }
        },
        {
            "aliases": null,
            "api_detail_url": "https://comicvine.gamespot.com/api/issue/4000-497132/",
            "cover_date": "2015-08-27",
            "date_added": "2015-08-08 01:23:26",
            "date_last_updated": "2015-08-26 12:58:03",
            "deck": null,
            "description": null,
            "has_staff_review": false,
            "id": 497132,
            "image": {
                "icon_url": "https://comicvine.gamespot.com/api/image/square_avatar/4733722-28.jpg",
                "medium_url": "https://comicvine.gamespot.com/api/image/scale_medium/4733722-28.jpg",
                "screen_url": "https://comicvine.gamespot.com/api/image/screen_medium/4733722-28.jpg",
                "screen_large_url": "https://comicvine.gamespot.com/api/image/screen_kubrick/4733722-28.jpg",
                "small_url": "https://comicvine.gamespot.com/api/image/scale_small/4733722-28.jpg",
                "super_url": "https://comicvine.gamespot.com/api/image/scale_large/4733722-28.jpg",
                "thumb_url": "https://comicvine.gamespot.com/api/image/scale_avatar/4733722-28.jpg",
                "tiny_url": "https://comicvine.gamespot.com/api/image/square_mini/4733722-28.jpg",
                "original_url": "https://comicvine.gamespot.com/api/image/original/4733722-28.jpg",
                "image_tags": "All Images"
            },
            "issue_number": "28",
            "name": "Vol. 28",
            "site_detail_url": "https://comicvine.gamespot.com/freezing-28-vol-28/4000-497132/",
            "store_date": "2015-08-27",
            "volume": {
                "api_detail_url": "https://comicvine.gamespot.com/api/volume/4050-45032/",
                "id": 45032,
                "name": "Freezing",
                "site_detail_url": "https://comicvine.gamespot.com/freezing/4050-45032/"
            }
        },
        {
            "aliases": null,
            "api_detail_url": "https://comicvine.gamespot.com/api/issue/4000-498729/",
            "cover_date": "2015-08-28",
            "date_added": "2015-08-28 16:32:35",
            "date_last_updated": "2015-08-29 14:28:43",
            "deck": null,
            "description": "<p><em>When a gang of armed thugs attack Wayne Industries, it's up to Tim Drake, aka Robin, to protect his students. But it's three on one, and Robin is unarmed…does he stand a chance without Batman's help?</em></p>",
            "has_staff_review": false,
            "id": 498729,
            "image": {
                "icon_url": "https://comicvine.gamespot.com/api/image/square_avatar/4772559-28.jpg",
                "medium_url": "https://comicvine.gamespot.com/api/image/scale_medium/4772559-28.jpg",
                "screen_url": "https://comicvine.gamespot.com/api/image/screen_medium/4772559-28.jpg",
                "screen_large_url": "https://comicvine.gamespot.com/api/image/screen_kubrick/4772559-28.jpg",
                "small_url": "https://comicvine.gamespot.com/api/image/scale_small/4772559-28.jpg",
                "super_url": "https://comicvine.gamespot.com/api/image/scale_large/4772559-28.jpg",
                "thumb_url": "https://comicvine.gamespot.com/api/image/scale_avatar/4772559-28.jpg",
                "tiny_url": "https://comicvine.gamespot.com/api/image/square_mini/4772559-28.jpg",
                "original_url": "https://comicvine.gamespot.com/api/image/original/4772559-28.jpg",
                "image_tags": "All Images"
            },
            "issue_number": "28",
            "name": "The Apprentice Part 2 of 2",
            "site_detail_url": "https://comicvine.gamespot.com/batman-arkham-knight-28-the-apprentice-part-2-of-2/4000-498729/",
            "store_date": "2015-08-28",
            "volume": {
                "api_detail_url": "https://comicvine.gamespot.com/api/volume/4050-80292/",
                "id": 80292,
                "name": "Batman: Arkham Knight",
                "site_detail_url": "https://comicvine.gamespot.com/batman-arkham-knight/4050-80292/"
            }
        },
        {
            "aliases": null,
            "api_detail_url": "https://comicvine.gamespot.com/api/issue/4000-499464/",
            "cover_date": "2015-08-31",
            "date_added": "2015-09-06 00:44:02",
            "date_last_updated": "2018-08-23 01:34:03",
            "deck": null,
            "description": null,
            "has_staff_review": false,
            "id": 499464,
            "image": {
                "icon_url": "https://comicvine.gamespot.com/api/image/square_avatar/4788036-28.jpg",
                "medium_url": "https://comicvine.gamespot.com/api/image/scale_medium/4788036-28.jpg",
                "screen_url": "https://comicvine.gamespot.com/api/image/screen_medium/4788036-28.jpg",
                "screen_large_url": "https://comicvine.gamespot.com/api/image/screen_kubrick/4788036-28.jpg",
                "small_url": "https://comicvine.gamespot.com/api/image/scale_small/4788036-28.jpg",
                "super_url": "https://comicvine.gamespot.com/api/image/scale_large/4788036-28.jpg",
                "thumb_url": "https://comicvine.gamespot.com/api/image/scale_avatar/4788036-28.jpg",
                "tiny_url": "https://comicvine.gamespot.com/api/image/square_mini/4788036-28.jpg",
                "original_url": "https://comicvine.gamespot.com/api/image/original/4788036-28.jpg",
                "image_tags": "All Images"
            },
            "issue_number": "28",
            "name": null,
            "site_detail_url": "https://comicvine.gamespot.com/comic-anthurium-28/4000-499464/",
            "store_date": "2015-07-10",
            "volume": {
                "api_detail_url": "https://comicvine.gamespot.com/api/volume/4050-67387/",
                "id": 67387,
                "name": "Comic Anthurium",
                "site_detail_url": "https://comicvine.gamespot.com/comic-anthurium/4050-67387/"
            }
        },
        {
            "aliases": null,
            "api_detail_url": "https://comicvine.gamespot.com/api/issue/4000-502209/",
            "cover_date": "2015-10-31",
            "date_added": "2015-10-06 03:41:31",
            "date_last_updated": "2015-10-07 16:16:10",
            "deck": null,
            "description": "<p><em>It’s a supernatural love-triangle showdown as the three publishers courting Muscle Man, Starla, Mordecai, and go to war with each other!</em></p><h4>List of covers and their creators:</h4><table data-max-width=\"true\"><thead><tr><th scope=\"col\">Cover</th><th scope=\"col\">Name</th><th scope=\"col\">Creator(s)</th><th scope=\"col\">Sidebar Location</th></tr></thead><tbody><tr><td>Reg</td><td>Regular Cover</td><td>Douglas Holgate</td><td>1</td></tr><tr><td>Sub</td><td>Subscription Cover</td><td>Rian Sygh</td><td>2</td></tr></tbody></table>",
            "has_staff_review": false,
            "id": 502209,
            "image": {
                "icon_url": "https://comicvine.gamespot.com/api/image/square_avatar/4841539-28.jpg",
                "medium_url": "https://comicvine.gamespot.com/api/image/scale_medium/4841539-28.jpg",
                "screen_url": "https://comicvine.gamespot.com/api/image/screen_medium/4841539-28.jpg",
                "screen_large_url": "https://comicvine.gamespot.com/api/image/screen_kubrick/4841539-28.jpg",
                "small_url": "https://comicvine.gamespot.com/api/image/scale_small/4841539-28.jpg",
                "super_url": "https://comicvine.gamespot.com/api/image/scale_large/4841539-28.jpg",
                "thumb_url": "https://comicvine.gamespot.com/api/image/scale_avatar/4841539-28.jpg",
                "tiny_url": "https://comicvine.gamespot.com/api/image/square_mini/4841539-28.jpg",
                "original_url": "https://comicvine.gamespot.com/api/image/original/4841539-28.jpg",
                "image_tags": "All Images"
            },
            "issue_number": "28",
            "name": "[Untitled]; Stakeout; Candy Economy",
            "site_detail_url": "https://comicvine.gamespot.com/regular-show-28-untitled-stakeout-candy-economy/4000-502209/",
            "store_date": "2015-10-07",
            "volume": {
                "api_detail_url": "https://comicvine.gamespot.com/api/volume/4050-61288/",
                "id": 61288,
                "name": "Regular Show",
                "site_detail_url": "https://comicvine.gamespot.com/regular-show/4050-61288/"
            }
        },
        {
            "aliases": null,
            "api_detail_url": "https://comicvine.gamespot.com/api/issue/4000-503522/",
            "cover_date": "2015-12-31",
            "date_added": "2015-10-20 03:43:09",
            "date_last_updated": "2015-10-23 11:45:43",
            "deck": null,
            "description": "<p><em>A look into the life of Wolfspider, the Australian Honor Guard member. When Queenslaw, a cartoon super hero team from Wolfspider’s youth, suddenly turns up as real heroes, he has to deal with his origin, his childhood dreams, and deadly danger. Guest art by Australian comics star Gary Chaloner (Jackaroo, Red Kelso, John Law). Plus: a fistful of Australian super-villains, too! It’s a whole theme thing!</em></p>",
            "has_staff_review": false,
            "id": 503522,
            "image": {
                "icon_url": "https://comicvine.gamespot.com/api/image/square_avatar/4865181-28.jpg",
                "medium_url": "https://comicvine.gamespot.com/api/image/scale_medium/4865181-28.jpg",
                "screen_url": "https://comicvine.gamespot.com/api/image/screen_medium/4865181-28.jpg",
                "screen_large_url": "https://comicvine.gamespot.com/api/image/screen_kubrick/4865181-28.jpg",
                "small_url": "https://comicvine.gamespot.com/api/image/scale_small/4865181-28.jpg",
                "super_url": "https://comicvine.gamespot.com/api/image/scale_large/4865181-28.jpg",
                "thumb_url": "https://comicvine.gamespot.com/api/image/scale_avatar/4865181-28.jpg",
                "tiny_url": "https://comicvine.gamespot.com/api/image/square_mini/4865181-28.jpg",
                "original_url": "https://comicvine.gamespot.com/api/image/original/4865181-28.jpg",
                "image_tags": "All Images"
            },
            "issue_number": "28",
            "name": "Yesterday's Heroes",
            "site_detail_url": "https://comicvine.gamespot.com/astro-city-28-yesterdays-heroes/4000-503522/",
            "store_date": "2015-10-21",
            "volume": {
                "api_detail_url": "https://comicvine.gamespot.com/api/volume/4050-62857/",
                "id": 62857,
                "name": "Astro City",
                "site_detail_url": "https://comicvine.gamespot.com/astro-city/4050-62857/"
            }
        },
        {
            "aliases": null,
            "api_detail_url": "https://comicvine.gamespot.com/api/issue/4000-503625/",
            "cover_date": "2015-10-31",
            "date_added": "2015-10-20 04:23:52",
            "date_last_updated": "2015-10-21 14:32:49",
            "deck": null,
            "description": "<p><em>Passerby</em></p><p><em>Chapter 14 of Avaiyo, Vol. 02</em></p><p><em>After centuries of slavery under the oppressive rule of the Tamiran Empire, the people of Xiltria were finally able to regain their freedom. It's been nearly eight years since the Era of Slavery, and the tides of peace are beginning to wash away. Subtle remnants of the exiled Tamiran Empire still live on and are starting to give way towards a new threat.</em></p><p><em>One such threat has been brought to the doorstep of Pegil Village. Helpless to defend themselves, they call out for help in hopes that someone will answer. With their pleas heard, Sekken and Iyo push forward into the depths of Daskin's Lair. Separated from each other, they must rely on their own skills to face the impending dangers.</em></p>",
            "has_staff_review": false,
            "id": 503625,
            "image": {
                "icon_url": "https://comicvine.gamespot.com/api/image/square_avatar/4865292-28.jpg",
                "medium_url": "https://comicvine.gamespot.com/api/image/scale_medium/4865292-28.jpg",
                "screen_url": "https://comicvine.gamespot.com/api/image/screen_medium/4865292-28.jpg",
                "screen_large_url": "https://comicvine.gamespot.com/api/image/screen_kubrick/4865292-28.jpg",
                "small_url": "https://comicvine.gamespot.com/api/image/scale_small/4865292-28.jpg",
                "super_url": "https://comicvine.gamespot.com/api/image/scale_large/4865292-28.jpg",
                "thumb_url": "https://comicvine.gamespot.com/api/image/scale_avatar/4865292-28.jpg",
                "tiny_url": "https://comicvine.gamespot.com/api/image/square_mini/4865292-28.jpg",
                "original_url": "https://comicvine.gamespot.com/api/image/original/4865292-28.jpg",
                "image_tags": "All Images"
            },
            "issue_number": "28",
            "name": "Passerby",
            "site_detail_url": "https://comicvine.gamespot.com/avaiyo-myriad-law-28-passerby/4000-503625/",
            "store_date": "2015-10-21",
            "volume": {
                "api_detail_url": "https://comicvine.gamespot.com/api/volume/4050-80799/",
                "id": 80799,
                "name": "Avaiyo: Myriad Law",
                "site_detail_url": "https://comicvine.gamespot.com/avaiyo-myriad-law/4050-80799/"
            }
        },
        {
            "aliases": null,
            "api_detail_url": "https://comicvine.gamespot.com/api/issue/4000-504508/",
            "cover_date": "2015-12-31",
            "date_added": "2015-10-28 10:16:23",
            "date_last_updated": "2015-11-17 15:35:17",
            "deck": "Halloween in Gotham introduces two new rogues to The Dynamic Duo!",
            "description": "<p><em>Two new additions to the ’66 Rogues Gallery are introduced in two stories. The Scarecrow is here to say “boo” to the good citizens of Gotham City, and to chase off the Caped Crusader. Then, a former henchman of King Tut has taken on a green, scaly look and roams the sewers under the city streets!</em></p>",
            "has_staff_review": false,
            "id": 504508,
            "image": {
                "icon_url": "https://comicvine.gamespot.com/api/image/square_avatar/4880072-28.jpg",
                "medium_url": "https://comicvine.gamespot.com/api/image/scale_medium/4880072-28.jpg",
                "screen_url": "https://comicvine.gamespot.com/api/image/screen_medium/4880072-28.jpg",
                "screen_large_url": "https://comicvine.gamespot.com/api/image/screen_kubrick/4880072-28.jpg",
                "small_url": "https://comicvine.gamespot.com/api/image/scale_small/4880072-28.jpg",
                "super_url": "https://comicvine.gamespot.com/api/image/scale_large/4880072-28.jpg",
                "thumb_url": "https://comicvine.gamespot.com/api/image/scale_avatar/4880072-28.jpg",
                "tiny_url": "https://comicvine.gamespot.com/api/image/square_mini/4880072-28.jpg",
                "original_url": "https://comicvine.gamespot.com/api/image/original/4880072-28.jpg",
                "image_tags": "All Images"
            },
            "issue_number": "28",
            "name": "Scarecrow Comes To Town",
            "site_detail_url": "https://comicvine.gamespot.com/batman-66-28-scarecrow-comes-to-town/4000-504508/",
            "store_date": "2015-10-28",
            "volume": {
                "api_detail_url": "https://comicvine.gamespot.com/api/volume/4050-65344/",
                "id": 65344,
                "name": "Batman '66",
                "site_detail_url": "https://comicvine.gamespot.com/batman-66/4050-65344/"
            }
        },
        {
            "aliases": null,
            "api_detail_url": "https://comicvine.gamespot.com/api/issue/4000-505477/",
            "cover_date": "2015-11-30",
            "date_added": "2015-11-10 01:59:26",
            "date_last_updated": "2016-08-20 22:26:42",
            "deck": null,
            "description": "<p><em>Monstrosities continue to spill out of the destruction Abe saw in Florida as he meets someone with answers about his role in the worldwide disaster.</em></p><p><em>Kicking off a two-parter full of revelations!</em></p>",
            "has_staff_review": false,
            "id": 505477,
            "image": {
                "icon_url": "https://comicvine.gamespot.com/api/image/square_avatar/4904812-28.jpg",
                "medium_url": "https://comicvine.gamespot.com/api/image/scale_medium/4904812-28.jpg",
                "screen_url": "https://comicvine.gamespot.com/api/image/screen_medium/4904812-28.jpg",
                "screen_large_url": "https://comicvine.gamespot.com/api/image/screen_kubrick/4904812-28.jpg",
                "small_url": "https://comicvine.gamespot.com/api/image/scale_small/4904812-28.jpg",
                "super_url": "https://comicvine.gamespot.com/api/image/scale_large/4904812-28.jpg",
                "thumb_url": "https://comicvine.gamespot.com/api/image/scale_avatar/4904812-28.jpg",
                "tiny_url": "https://comicvine.gamespot.com/api/image/square_mini/4904812-28.jpg",
                "original_url": "https://comicvine.gamespot.com/api/image/original/4904812-28.jpg",
                "image_tags": "All Images"
            },
            "issue_number": "28",
            "name": "The Garden (II), Part 1",
            "site_detail_url": "https://comicvine.gamespot.com/abe-sapien-28-the-garden-ii-part-1/4000-505477/",
            "store_date": "2015-11-11",
            "volume": {
                "api_detail_url": "https://comicvine.gamespot.com/api/volume/4050-59507/",
                "id": 59507,
                "name": "Abe Sapien",
                "site_detail_url": "https://comicvine.gamespot.com/abe-sapien/4050-59507/"
            }
        },
        {
            "aliases": null,
            "api_detail_url": "https://comicvine.gamespot.com/api/issue/4000-505750/",
            "cover_date": "2015-10-31",
            "date_added": "2015-11-12 14:58:18",
            "date_last_updated": "2016-01-22 05:02:24",
            "deck": null,
            "description": null,
            "has_staff_review": false,
            "id": 505750,
            "image": {
                "icon_url": "https://comicvine.gamespot.com/api/image/square_avatar/4905652-x-men%20%28v4%29%2028%20-%20octobre%202015.jpg",
                "medium_url": "https://comicvine.gamespot.com/api/image/scale_medium/4905652-x-men%20%28v4%29%2028%20-%20octobre%202015.jpg",
                "screen_url": "https://comicvine.gamespot.com/api/image/screen_medium/4905652-x-men%20%28v4%29%2028%20-%20octobre%202015.jpg",
                "screen_large_url": "https://comicvine.gamespot.com/api/image/screen_kubrick/4905652-x-men%20%28v4%29%2028%20-%20octobre%202015.jpg",
                "small_url": "https://comicvine.gamespot.com/api/image/scale_small/4905652-x-men%20%28v4%29%2028%20-%20octobre%202015.jpg",
                "super_url": "https://comicvine.gamespot.com/api/image/scale_large/4905652-x-men%20%28v4%29%2028%20-%20octobre%202015.jpg",
                "thumb_url": "https://comicvine.gamespot.com/api/image/scale_avatar/4905652-x-men%20%28v4%29%2028%20-%20octobre%202015.jpg",
                "tiny_url": "https://comicvine.gamespot.com/api/image/square_mini/4905652-x-men%20%28v4%29%2028%20-%20octobre%202015.jpg",
                "original_url": "https://comicvine.gamespot.com/api/image/original/4905652-x-men%20%28v4%29%2028%20-%20octobre%202015.jpg",
                "image_tags": "All Images"
            },
            "issue_number": "28",
            "name": "Le Vortex Noir (3/7)",
            "site_detail_url": "https://comicvine.gamespot.com/x-men-28-le-vortex-noir-37/4000-505750/",
            "store_date": "2015-10-07",
            "volume": {
                "api_detail_url": "https://comicvine.gamespot.com/api/volume/4050-65022/",
                "id": 65022,
                "name": "X-Men",
                "site_detail_url": "https://comicvine.gamespot.com/x-men/4050-65022/"
            }
        },
        {
            "aliases": null,
            "api_detail_url": "https://comicvine.gamespot.com/api/issue/4000-508207/",
            "cover_date": "2015-12-31",
            "date_added": "2015-12-13 22:25:50",
            "date_last_updated": "2015-12-13 22:34:51",
            "deck": null,
            "description": "<p><em>FutureQuake is back! The finest talents in the small press are here again to save you from boredom. Where else in the printed world can you get this much variety for such a small outlay? 48 pages for only $.99 and a wraparound cover by artist Steven Austin. It would be an insult to all of creation to ask for less!</em></p><p><em>Barry's Nose by writer Rory McConville and artist Scott Twells</em></p><p><em>Cop Killer by writer Tim Perry and artist Joe Palmer</em></p><p><em>Monitors by writer Jonathan Harris and artist Wesley St Clair</em></p><p><em>Old by writer Michelle Wilkinson and artist A I Miller</em></p><p><em>Orionid by writer Virgil Yendell and artist Neil Sims</em></p><p><em>Peaceful Farewell by writer Blas Bigatti and artist Adam Caudill</em></p><p><em>Revolution 1010 by writer Mike Yeoman and artist Steven Austin</em></p><p><em>The Final Boss by writer Dave Cook and artist RH Stewart</em></p><p><em>The Long Sleep by writer Robert Lefebvre and artist David Valente</em></p><p><em>The Gods Tear by writer JJ Robinson and artist Alex Paterson</em></p><p><em>Wanted by writer Marcello Bondi and artist Mattia Marini</em></p>",
            "has_staff_review": false,
            "id": 508207,
            "image": {
                "icon_url": "https://comicvine.gamespot.com/api/image/square_avatar/4954249-28.jpg",
                "medium_url": "https://comicvine.gamespot.com/api/image/scale_medium/4954249-28.jpg",
                "screen_url": "https://comicvine.gamespot.com/api/image/screen_medium/4954249-28.jpg",
                "screen_large_url": "https://comicvine.gamespot.com/api/image/screen_kubrick/4954249-28.jpg",
                "small_url": "https://comicvine.gamespot.com/api/image/scale_small/4954249-28.jpg",
                "super_url": "https://comicvine.gamespot.com/api/image/scale_large/4954249-28.jpg",
                "thumb_url": "https://comicvine.gamespot.com/api/image/scale_avatar/4954249-28.jpg",
                "tiny_url": "https://comicvine.gamespot.com/api/image/square_mini/4954249-28.jpg",
                "original_url": "https://comicvine.gamespot.com/api/image/original/4954249-28.jpg",
                "image_tags": "All Images"
            },
            "issue_number": "28",
            "name": null,
            "site_detail_url": "https://comicvine.gamespot.com/futurequake-28/4000-508207/",
            "store_date": "2015-12-09",
            "volume": {
                "api_detail_url": "https://comicvine.gamespot.com/api/volume/4050-27591/",
                "id": 27591,
                "name": "FutureQuake",
                "site_detail_url": "https://comicvine.gamespot.com/futurequake/4050-27591/"
            }
        },
        {
            "aliases": null,
            "api_detail_url": "https://comicvine.gamespot.com/api/issue/4000-510456/",
            "cover_date": "2015-11-30",
            "date_added": "2016-01-04 23:38:58",
            "date_last_updated": "2016-01-04 23:39:52",
            "deck": null,
            "description": "<p> Translates Avengers #40 &amp; New Avengers #29.</p>",
            "has_staff_review": false,
            "id": 510456,
            "image": {
                "icon_url": "https://comicvine.gamespot.com/api/image/square_avatar/4984927-4608150148-AVENG.jpg",
                "medium_url": "https://comicvine.gamespot.com/api/image/scale_medium/4984927-4608150148-AVENG.jpg",
                "screen_url": "https://comicvine.gamespot.com/api/image/screen_medium/4984927-4608150148-AVENG.jpg",
                "screen_large_url": "https://comicvine.gamespot.com/api/image/screen_kubrick/4984927-4608150148-AVENG.jpg",
                "small_url": "https://comicvine.gamespot.com/api/image/scale_small/4984927-4608150148-AVENG.jpg",
                "super_url": "https://comicvine.gamespot.com/api/image/scale_large/4984927-4608150148-AVENG.jpg",
                "thumb_url": "https://comicvine.gamespot.com/api/image/scale_avatar/4984927-4608150148-AVENG.jpg",
                "tiny_url": "https://comicvine.gamespot.com/api/image/square_mini/4984927-4608150148-AVENG.jpg",
                "original_url": "https://comicvine.gamespot.com/api/image/original/4984927-4608150148-AVENG.jpg",
                "image_tags": "All Images"
            },
            "issue_number": "28",
            "name": null,
            "site_detail_url": "https://comicvine.gamespot.com/avengers-28/4000-510456/",
            "store_date": "2015-10-13",
            "volume": {
                "api_detail_url": "https://comicvine.gamespot.com/api/volume/4050-67397/",
                "id": 67397,
                "name": "Avengers",
                "site_detail_url": "https://comicvine.gamespot.com/avengers/4050-67397/"
            }
        },
        {
            "aliases": null,
            "api_detail_url": "https://comicvine.gamespot.com/api/issue/4000-511156/",
            "cover_date": "2015-11-30",
            "date_added": "2016-01-15 02:04:03",
            "date_last_updated": "2016-01-15 02:07:56",
            "deck": null,
            "description": "<p> Translates Guardians of the Galaxy #25, Nova #28 &amp; Legendary Star-Lord #10.</p>",
            "has_staff_review": false,
            "id": 511156,
            "image": {
                "icon_url": "https://comicvine.gamespot.com/api/image/square_avatar/5000742-0553375066-DIENE.jpg",
                "medium_url": "https://comicvine.gamespot.com/api/image/scale_medium/5000742-0553375066-DIENE.jpg",
                "screen_url": "https://comicvine.gamespot.com/api/image/screen_medium/5000742-0553375066-DIENE.jpg",
                "screen_large_url": "https://comicvine.gamespot.com/api/image/screen_kubrick/5000742-0553375066-DIENE.jpg",
                "small_url": "https://comicvine.gamespot.com/api/image/scale_small/5000742-0553375066-DIENE.jpg",
                "super_url": "https://comicvine.gamespot.com/api/image/scale_large/5000742-0553375066-DIENE.jpg",
                "thumb_url": "https://comicvine.gamespot.com/api/image/scale_avatar/5000742-0553375066-DIENE.jpg",
                "tiny_url": "https://comicvine.gamespot.com/api/image/square_mini/5000742-0553375066-DIENE.jpg",
                "original_url": "https://comicvine.gamespot.com/api/image/original/5000742-0553375066-DIENE.jpg",
                "image_tags": "All Images"
            },
            "issue_number": "28",
            "name": null,
            "site_detail_url": "https://comicvine.gamespot.com/die-neuen-x-men-28/4000-511156/",
            "store_date": "2015-10-27",
            "volume": {
                "api_detail_url": "https://comicvine.gamespot.com/api/volume/4050-65646/",
                "id": 65646,
                "name": "Die Neuen X-Men",
                "site_detail_url": "https://comicvine.gamespot.com/die-neuen-x-men/4050-65646/"
            }
        },
        {
            "aliases": null,
            "api_detail_url": "https://comicvine.gamespot.com/api/issue/4000-511986/",
            "cover_date": "2015-11-30",
            "date_added": "2016-01-23 13:39:44",
            "date_last_updated": "2017-02-15 15:39:30",
            "deck": null,
            "description": "<p> Translates Amazing Spider-Man #14 &amp; Spider-Verse #1-2.</p>",
            "has_staff_review": false,
            "id": 511986,
            "image": {
                "icon_url": "https://comicvine.gamespot.com/api/image/square_avatar/5016434-5524611147-SPIDE.jpg",
                "medium_url": "https://comicvine.gamespot.com/api/image/scale_medium/5016434-5524611147-SPIDE.jpg",
                "screen_url": "https://comicvine.gamespot.com/api/image/screen_medium/5016434-5524611147-SPIDE.jpg",
                "screen_large_url": "https://comicvine.gamespot.com/api/image/screen_kubrick/5016434-5524611147-SPIDE.jpg",
                "small_url": "https://comicvine.gamespot.com/api/image/scale_small/5016434-5524611147-SPIDE.jpg",
                "super_url": "https://comicvine.gamespot.com/api/image/scale_large/5016434-5524611147-SPIDE.jpg",
                "thumb_url": "https://comicvine.gamespot.com/api/image/scale_avatar/5016434-5524611147-SPIDE.jpg",
                "tiny_url": "https://comicvine.gamespot.com/api/image/square_mini/5016434-5524611147-SPIDE.jpg",
                "original_url": "https://comicvine.gamespot.com/api/image/original/5016434-5524611147-SPIDE.jpg",
                "image_tags": "All Images"
            },
            "issue_number": "28",
            "name": null,
            "site_detail_url": "https://comicvine.gamespot.com/spider-man-28/4000-511986/",
            "store_date": "2015-10-13",
            "volume": {
                "api_detail_url": "https://comicvine.gamespot.com/api/volume/4050-87487/",
                "id": 87487,
                "name": "Spider-Man",
                "site_detail_url": "https://comicvine.gamespot.com/spider-man/4050-87487/"
            }
        },
        {
            "aliases": null,
            "api_detail_url": "https://comicvine.gamespot.com/api/issue/4000-519982/",
            "cover_date": "2016-02-29",
            "date_added": "2016-03-13 23:14:56",
            "date_last_updated": "2017-02-24 13:43:11",
            "deck": null,
            "description": null,
            "has_staff_review": false,
            "id": 519982,
            "image": {
                "icon_url": "https://comicvine.gamespot.com/api/image/square_avatar/5107452-wwwww.jpg",
                "medium_url": "https://comicvine.gamespot.com/api/image/scale_medium/5107452-wwwww.jpg",
                "screen_url": "https://comicvine.gamespot.com/api/image/screen_medium/5107452-wwwww.jpg",
                "screen_large_url": "https://comicvine.gamespot.com/api/image/screen_kubrick/5107452-wwwww.jpg",
                "small_url": "https://comicvine.gamespot.com/api/image/scale_small/5107452-wwwww.jpg",
                "super_url": "https://comicvine.gamespot.com/api/image/scale_large/5107452-wwwww.jpg",
                "thumb_url": "https://comicvine.gamespot.com/api/image/scale_avatar/5107452-wwwww.jpg",
                "tiny_url": "https://comicvine.gamespot.com/api/image/square_mini/5107452-wwwww.jpg",
                "original_url": "https://comicvine.gamespot.com/api/image/original/5107452-wwwww.jpg",
                "image_tags": "All Images"
            },
            "issue_number": "28",
            "name": "Vol. 28",
            "site_detail_url": "https://comicvine.gamespot.com/comic-milf-28-vol-28/4000-519982/",
            "store_date": "2015-12-24",
            "volume": {
                "api_detail_url": "https://comicvine.gamespot.com/api/volume/4050-68872/",
                "id": 68872,
                "name": "Comic MILF",
                "site_detail_url": "https://comicvine.gamespot.com/comic-milf/4050-68872/"
            }
        },
        {
            "aliases": null,
            "api_detail_url": "https://comicvine.gamespot.com/api/issue/4000-521139/",
            "cover_date": "2016-04-30",
            "date_added": "2016-03-21 01:42:30",
            "date_last_updated": "2016-03-21 01:43:03",
            "deck": null,
            "description": null,
            "has_staff_review": false,
            "id": 521139,
            "image": {
                "icon_url": "https://comicvine.gamespot.com/api/image/square_avatar/5108584-wwwww.jpg",
                "medium_url": "https://comicvine.gamespot.com/api/image/scale_medium/5108584-wwwww.jpg",
                "screen_url": "https://comicvine.gamespot.com/api/image/screen_medium/5108584-wwwww.jpg",
                "screen_large_url": "https://comicvine.gamespot.com/api/image/screen_kubrick/5108584-wwwww.jpg",
                "small_url": "https://comicvine.gamespot.com/api/image/scale_small/5108584-wwwww.jpg",
                "super_url": "https://comicvine.gamespot.com/api/image/scale_large/5108584-wwwww.jpg",
                "thumb_url": "https://comicvine.gamespot.com/api/image/scale_avatar/5108584-wwwww.jpg",
                "tiny_url": "https://comicvine.gamespot.com/api/image/square_mini/5108584-wwwww.jpg",
                "original_url": "https://comicvine.gamespot.com/api/image/original/5108584-wwwww.jpg",
                "image_tags": "All Images"
            },
            "issue_number": "28",
            "name": null,
            "site_detail_url": "https://comicvine.gamespot.com/comic-x-eros-28/4000-521139/",
            "store_date": "2015-02-26",
            "volume": {
                "api_detail_url": "https://comicvine.gamespot.com/api/volume/4050-89126/",
                "id": 89126,
                "name": "Comic X-Eros",
                "site_detail_url": "https://comicvine.gamespot.com/comic-xeros/4050-89126/"
            }
        },
        {
            "aliases": null,
            "api_detail_url": "https://comicvine.gamespot.com/api/issue/4000-524529/",
            "cover_date": "2015-01-31",
            "date_added": "2016-04-11 12:23:32",
            "date_last_updated": "2016-05-05 11:10:58",
            "deck": null,
            "description": null,
            "has_staff_review": false,
            "id": 524529,
            "image": {
                "icon_url": "https://comicvine.gamespot.com/api/image/square_avatar/5146209-28.jpg",
                "medium_url": "https://comicvine.gamespot.com/api/image/scale_medium/5146209-28.jpg",
                "screen_url": "https://comicvine.gamespot.com/api/image/screen_medium/5146209-28.jpg",
                "screen_large_url": "https://comicvine.gamespot.com/api/image/screen_kubrick/5146209-28.jpg",
                "small_url": "https://comicvine.gamespot.com/api/image/scale_small/5146209-28.jpg",
                "super_url": "https://comicvine.gamespot.com/api/image/scale_large/5146209-28.jpg",
                "thumb_url": "https://comicvine.gamespot.com/api/image/scale_avatar/5146209-28.jpg",
                "tiny_url": "https://comicvine.gamespot.com/api/image/square_mini/5146209-28.jpg",
                "original_url": "https://comicvine.gamespot.com/api/image/original/5146209-28.jpg",
                "image_tags": "All Images"
            },
            "issue_number": "28",
            "name": "Vol. 28",
            "site_detail_url": "https://comicvine.gamespot.com/baby-steps-28-vol-28/4000-524529/",
            "store_date": "2015-01-30",
            "volume": {
                "api_detail_url": "https://comicvine.gamespot.com/api/volume/4050-69047/",
                "id": 69047,
                "name": "Baby Steps",
                "site_detail_url": "https://comicvine.gamespot.com/baby-steps/4050-69047/"
            }
        },
        {
            "aliases": null,
            "api_detail_url": "https://comicvine.gamespot.com/api/issue/4000-524540/",
            "cover_date": "2015-07-31",
            "date_added": "2016-04-11 12:23:58",
            "date_last_updated": "2016-05-05 11:14:35",
            "deck": null,
            "description": null,
            "has_staff_review": false,
            "id": 524540,
            "image": {
                "icon_url": "https://comicvine.gamespot.com/api/image/square_avatar/5146222-28.jpg",
                "medium_url": "https://comicvine.gamespot.com/api/image/scale_medium/5146222-28.jpg",
                "screen_url": "https://comicvine.gamespot.com/api/image/screen_medium/5146222-28.jpg",
                "screen_large_url": "https://comicvine.gamespot.com/api/image/screen_kubrick/5146222-28.jpg",
                "small_url": "https://comicvine.gamespot.com/api/image/scale_small/5146222-28.jpg",
                "super_url": "https://comicvine.gamespot.com/api/image/scale_large/5146222-28.jpg",
                "thumb_url": "https://comicvine.gamespot.com/api/image/scale_avatar/5146222-28.jpg",
                "tiny_url": "https://comicvine.gamespot.com/api/image/square_mini/5146222-28.jpg",
                "original_url": "https://comicvine.gamespot.com/api/image/original/5146222-28.jpg",
                "image_tags": "All Images"
            },
            "issue_number": "28",
            "name": "Vol. 28",
            "site_detail_url": "https://comicvine.gamespot.com/beelzebub-28-vol-28/4000-524540/",
            "store_date": "2015-07-17",
            "volume": {
                "api_detail_url": "https://comicvine.gamespot.com/api/volume/4050-64956/",
                "id": 64956,
                "name": "Beelzebub",
                "site_detail_url": "https://comicvine.gamespot.com/beelzebub/4050-64956/"
            }
        },
        {
            "aliases": null,
            "api_detail_url": "https://comicvine.gamespot.com/api/issue/4000-526143/",
            "cover_date": "2015-12-18",
            "date_added": "2016-04-19 06:49:19",
            "date_last_updated": "2016-04-21 00:03:34",
            "deck": null,
            "description": null,
            "has_staff_review": false,
            "id": 526143,
            "image": {
                "icon_url": "https://comicvine.gamespot.com/api/image/square_avatar/5160466-28.jpg",
                "medium_url": "https://comicvine.gamespot.com/api/image/scale_medium/5160466-28.jpg",
                "screen_url": "https://comicvine.gamespot.com/api/image/screen_medium/5160466-28.jpg",
                "screen_large_url": "https://comicvine.gamespot.com/api/image/screen_kubrick/5160466-28.jpg",
                "small_url": "https://comicvine.gamespot.com/api/image/scale_small/5160466-28.jpg",
                "super_url": "https://comicvine.gamespot.com/api/image/scale_large/5160466-28.jpg",
                "thumb_url": "https://comicvine.gamespot.com/api/image/scale_avatar/5160466-28.jpg",
                "tiny_url": "https://comicvine.gamespot.com/api/image/square_mini/5160466-28.jpg",
                "original_url": "https://comicvine.gamespot.com/api/image/original/5160466-28.jpg",
                "image_tags": "All Images"
            },
            "issue_number": "28",
            "name": "Volume 28",
            "site_detail_url": "https://comicvine.gamespot.com/kyokai-no-rinne-28-volume-28/4000-526143/",
            "store_date": "2015-12-18",
            "volume": {
                "api_detail_url": "https://comicvine.gamespot.com/api/volume/4050-58844/",
                "id": 58844,
                "name": "Kyokai no Rinne",
                "site_detail_url": "https://comicvine.gamespot.com/kyokai-no-rinne/4050-58844/"
            }
        },
        {
            "aliases": null,
            "api_detail_url": "https://comicvine.gamespot.com/api/issue/4000-559317/",
            "cover_date": "2015-10-31",
            "date_added": "2016-11-26 05:36:33",
            "date_last_updated": "2017-04-15 17:59:42",
            "deck": null,
            "description": null,
            "has_staff_review": false,
            "id": 559317,
            "image": {
                "icon_url": "https://comicvine.gamespot.com/api/image/square_avatar/5551131-28.jpg",
                "medium_url": "https://comicvine.gamespot.com/api/image/scale_medium/5551131-28.jpg",
                "screen_url": "https://comicvine.gamespot.com/api/image/screen_medium/5551131-28.jpg",
                "screen_large_url": "https://comicvine.gamespot.com/api/image/screen_kubrick/5551131-28.jpg",
                "small_url": "https://comicvine.gamespot.com/api/image/scale_small/5551131-28.jpg",
                "super_url": "https://comicvine.gamespot.com/api/image/scale_large/5551131-28.jpg",
                "thumb_url": "https://comicvine.gamespot.com/api/image/scale_avatar/5551131-28.jpg",
                "tiny_url": "https://comicvine.gamespot.com/api/image/square_mini/5551131-28.jpg",
                "original_url": "https://comicvine.gamespot.com/api/image/original/5551131-28.jpg",
                "image_tags": "All Images"
            },
            "issue_number": "28",
            "name": "Père et Fils",
            "site_detail_url": "https://comicvine.gamespot.com/beelzebub-28-pere-et-fils/4000-559317/",
            "store_date": "2015-10-21",
            "volume": {
                "api_detail_url": "https://comicvine.gamespot.com/api/volume/4050-95883/",
                "id": 95883,
                "name": "Beelzebub",
                "site_detail_url": "https://comicvine.gamespot.com/beelzebub/4050-95883/"
            }
        },
        {
            "aliases": null,
            "api_detail_url": "https://comicvine.gamespot.com/api/issue/4000-562071/",
            "cover_date": "2015-09-01",
            "date_added": "2016-11-28 06:17:09",
            "date_last_updated": "2018-09-15 19:33:12",
            "deck": "Dragonero affronta una creatura da leggenda: il mostruoso Kraken di aria!",
            "description": "<p><em>Una tranquilla cittadina costiera viene attaccata da un gigantesco Kraken di aria, come non se ne vedevano da secoli. Dragonero viene convocato d'urgenza alla corporazione dei naturalisti imperiali, presso Vahlendart, dove riceve le istruzioni per la sua nuova missione: volare fino alle estreme coste orientali del mare Eolanisuhre e unirsi ad un gruppo di cacciatori chiamati \"i folli di Queman\". La sua missione: rintracciare e uccidere il Kraken!</em></p>",
            "has_staff_review": false,
            "id": 562071,
            "image": {
                "icon_url": "https://comicvine.gamespot.com/api/image/square_avatar/5557444-28.jpg",
                "medium_url": "https://comicvine.gamespot.com/api/image/scale_medium/5557444-28.jpg",
                "screen_url": "https://comicvine.gamespot.com/api/image/screen_medium/5557444-28.jpg",
                "screen_large_url": "https://comicvine.gamespot.com/api/image/screen_kubrick/5557444-28.jpg",
                "small_url": "https://comicvine.gamespot.com/api/image/scale_small/5557444-28.jpg",
                "super_url": "https://comicvine.gamespot.com/api/image/scale_large/5557444-28.jpg",
                "thumb_url": "https://comicvine.gamespot.com/api/image/scale_avatar/5557444-28.jpg",
                "tiny_url": "https://comicvine.gamespot.com/api/image/square_mini/5557444-28.jpg",
                "original_url": "https://comicvine.gamespot.com/api/image/original/5557444-28.jpg",
                "image_tags": "All Images"
            },
            "issue_number": "28",
            "name": "Cacciatori di Kraken",
            "site_detail_url": "https://comicvine.gamespot.com/dragonero-28-cacciatori-di-kraken/4000-562071/",
            "store_date": "2015-09-09",
            "volume": {
                "api_detail_url": "https://comicvine.gamespot.com/api/volume/4050-67599/",
                "id": 67599,
                "name": "Dragonero",
                "site_detail_url": "https://comicvine.gamespot.com/dragonero/4050-67599/"
            }
        },
        {
            "aliases": null,
            "api_detail_url": "https://comicvine.gamespot.com/api/issue/4000-562147/",
            "cover_date": "2015-01-01",
            "date_added": "2016-11-28 06:21:01",
            "date_last_updated": "2018-10-27 00:36:44",
            "deck": "Nella Roma del 1825, un fantasma omicida insanguina Castel Sant'Angelo!",
            "description": "<p><em>Nella Roma del 1825 non fermentano solo i primi germi del patriottismo carbonaro e le trame delle tante società segrete… Ben altri misteri funestano le notti della futura capitale d’Italia. L’antico Castel Sant’Angelo è infatti sede di alcune oscure morti e tra le sue mura si dice alberghi un fantasma omicida. È un enigma che solo la mente fredda ed erudita di un italico Sherlock Holmes potrebbe sciogliere, la mente di un uomo d’azione senza paura (o quasi). La mente inflessibile di… Mercurio Loi!</em></p>",
            "has_staff_review": false,
            "id": 562147,
            "image": {
                "icon_url": "https://comicvine.gamespot.com/api/image/square_avatar/5557551-28.jpg",
                "medium_url": "https://comicvine.gamespot.com/api/image/scale_medium/5557551-28.jpg",
                "screen_url": "https://comicvine.gamespot.com/api/image/screen_medium/5557551-28.jpg",
                "screen_large_url": "https://comicvine.gamespot.com/api/image/screen_kubrick/5557551-28.jpg",
                "small_url": "https://comicvine.gamespot.com/api/image/scale_small/5557551-28.jpg",
                "super_url": "https://comicvine.gamespot.com/api/image/scale_large/5557551-28.jpg",
                "thumb_url": "https://comicvine.gamespot.com/api/image/scale_avatar/5557551-28.jpg",
                "tiny_url": "https://comicvine.gamespot.com/api/image/square_mini/5557551-28.jpg",
                "original_url": "https://comicvine.gamespot.com/api/image/original/5557551-28.jpg",
                "image_tags": "All Images"
            },
            "issue_number": "28",
            "name": "Mercurio Loi",
            "site_detail_url": "https://comicvine.gamespot.com/le-storie-28-mercurio-loi/4000-562147/",
            "store_date": "2015-01-10",
            "volume": {
                "api_detail_url": "https://comicvine.gamespot.com/api/volume/4050-85062/",
                "id": 85062,
                "name": "Le Storie",
                "site_detail_url": "https://comicvine.gamespot.com/le-storie/4050-85062/"
            }
        },
        {
            "aliases": null,
            "api_detail_url": "https://comicvine.gamespot.com/api/issue/4000-568022/",
            "cover_date": "2015-08-12",
            "date_added": "2016-12-16 22:48:18",
            "date_last_updated": "2017-08-12 23:12:39",
            "deck": null,
            "description": null,
            "has_staff_review": false,
            "id": 568022,
            "image": {
                "icon_url": "https://comicvine.gamespot.com/api/image/square_avatar/5594761-28.jpg",
                "medium_url": "https://comicvine.gamespot.com/api/image/scale_medium/5594761-28.jpg",
                "screen_url": "https://comicvine.gamespot.com/api/image/screen_medium/5594761-28.jpg",
                "screen_large_url": "https://comicvine.gamespot.com/api/image/screen_kubrick/5594761-28.jpg",
                "small_url": "https://comicvine.gamespot.com/api/image/scale_small/5594761-28.jpg",
                "super_url": "https://comicvine.gamespot.com/api/image/scale_large/5594761-28.jpg",
                "thumb_url": "https://comicvine.gamespot.com/api/image/scale_avatar/5594761-28.jpg",
                "tiny_url": "https://comicvine.gamespot.com/api/image/square_mini/5594761-28.jpg",
                "original_url": "https://comicvine.gamespot.com/api/image/original/5594761-28.jpg",
                "image_tags": "All Images"
            },
            "issue_number": "28",
            "name": "Vol. 28",
            "site_detail_url": "https://comicvine.gamespot.com/chihayafuru-28-vol-28/4000-568022/",
            "store_date": "2015-08-12",
            "volume": {
                "api_detail_url": "https://comicvine.gamespot.com/api/volume/4050-49590/",
                "id": 49590,
                "name": "Chihayafuru",
                "site_detail_url": "https://comicvine.gamespot.com/chihayafuru/4050-49590/"
            }
        },
        {
            "aliases": null,
            "api_detail_url": "https://comicvine.gamespot.com/api/issue/4000-573943/",
            "cover_date": "2015-10-01",
            "date_added": "2016-12-31 22:13:30",
            "date_last_updated": "2017-08-11 08:49:45",
            "deck": null,
            "description": null,
            "has_staff_review": false,
            "id": 573943,
            "image": {
                "icon_url": "https://comicvine.gamespot.com/api/image/square_avatar/5624025-28.jpg",
                "medium_url": "https://comicvine.gamespot.com/api/image/scale_medium/5624025-28.jpg",
                "screen_url": "https://comicvine.gamespot.com/api/image/screen_medium/5624025-28.jpg",
                "screen_large_url": "https://comicvine.gamespot.com/api/image/screen_kubrick/5624025-28.jpg",
                "small_url": "https://comicvine.gamespot.com/api/image/scale_small/5624025-28.jpg",
                "super_url": "https://comicvine.gamespot.com/api/image/scale_large/5624025-28.jpg",
                "thumb_url": "https://comicvine.gamespot.com/api/image/scale_avatar/5624025-28.jpg",
                "tiny_url": "https://comicvine.gamespot.com/api/image/square_mini/5624025-28.jpg",
                "original_url": "https://comicvine.gamespot.com/api/image/original/5624025-28.jpg",
                "image_tags": "All Images"
            },
            "issue_number": "28",
            "name": "Vol. 28",
            "site_detail_url": "https://comicvine.gamespot.com/kocchi-muite-miiko-28-vol-28/4000-573943/",
            "store_date": "2015-10-01",
            "volume": {
                "api_detail_url": "https://comicvine.gamespot.com/api/volume/4050-97605/",
                "id": 97605,
                "name": "Kocchi Muite! Miiko",
                "site_detail_url": "https://comicvine.gamespot.com/kocchi-muite-miiko/4050-97605/"
            }
        },
        {
            "aliases": null,
            "api_detail_url": "https://comicvine.gamespot.com/api/issue/4000-657524/",
            "cover_date": "2015-10-31",
            "date_added": "2018-02-03 03:02:51",
            "date_last_updated": "2018-02-09 22:01:16",
            "deck": null,
            "description": null,
            "has_staff_review": false,
            "id": 657524,
            "image": {
                "icon_url": "https://comicvine.gamespot.com/api/image/square_avatar/6261172-28.jpg",
                "medium_url": "https://comicvine.gamespot.com/api/image/scale_medium/6261172-28.jpg",
                "screen_url": "https://comicvine.gamespot.com/api/image/screen_medium/6261172-28.jpg",
                "screen_large_url": "https://comicvine.gamespot.com/api/image/screen_kubrick/6261172-28.jpg",
                "small_url": "https://comicvine.gamespot.com/api/image/scale_small/6261172-28.jpg",
                "super_url": "https://comicvine.gamespot.com/api/image/scale_large/6261172-28.jpg",
                "thumb_url": "https://comicvine.gamespot.com/api/image/scale_avatar/6261172-28.jpg",
                "tiny_url": "https://comicvine.gamespot.com/api/image/square_mini/6261172-28.jpg",
                "original_url": "https://comicvine.gamespot.com/api/image/original/6261172-28.jpg",
                "image_tags": "All Images"
            },
            "issue_number": "28",
            "name": null,
            "site_detail_url": "https://comicvine.gamespot.com/itan-28/4000-657524/",
            "store_date": "2015-10-07",
            "volume": {
                "api_detail_url": "https://comicvine.gamespot.com/api/volume/4050-108375/",
                "id": 108375,
                "name": "ITAN",
                "site_detail_url": "https://comicvine.gamespot.com/i-t-a-n/4050-108375/"
            }
        }
    ]
}
